{
  "teams": [
    {
      "ID": "700",
      "EMAIL": "deandicarlo@yopmail.com",
      "STATUS": "active",
      "LOGO": "http://app.homecaravan.net/uploads/logo_company/20170815233517.jpg",
      "PHOTO": "http://app.homecaravan.net/uploads/account_avatar/20170612194243.jpg",
      "FIRST_NAME": "Dean",
      "LAST_NAME": "DiCarlo",
      "PHONE": "(314) 524-3495",
      "ACTION_REQUIRED": "yes",
      "ACTION_ACTIVE": "1",
      "INVITED_BY": "0",
      "USER_ID": "700",
      "COMPANY": "Weichert",
      "LISTING_ID": "175",
      "ROLE_ID": "Agent",
      "RECEPTIONIST": "no",
      "MESSAGE_COUNT": "0",
      "COMPANY_ADDRESS_1":"8081 Garfield Ave",
      "COMPANY_ADDRESS_2":"Huntington Beach, California"
    },
    {
      "ID": "701",
      "EMAIL": "christine@remeorealty.com",
      "STATUS": "active",
      "LOGO": "http://app.homecaravan.net/uploads/logo_company/20170815233517.jpg",
      "PHOTO": "http://app.homecaravan.net/uploads/account_avatar/20170612194421.jpg",
      "FIRST_NAME": "Christine",
      "LAST_NAME": "DiCarlo",
      "PHONE": "+(314) 524-3490",
      "ACTION_REQUIRED": "yes",
      "ACTION_ACTIVE": "1",
      "INVITED_BY": "0",
      "USER_ID": "701",
      "COMPANY": "Weichert",
      "LISTING_ID": "175",
      "ROLE_ID": "Agent",
      "RECEPTIONIST": "yes",
      "MESSAGE_COUNT": "28",
      "COMPANY_ADDRESS_1":"8081 Garfield Ave",
      "COMPANY_ADDRESS_2":"Huntington Beach, California"
    },
    {
      "ID": "702",
      "EMAIL": "Anthony@yopmail.com",
      "STATUS": "active",
      "PHOTO": "http://app.homecaravan.net/uploads/account_avatar/20170717234139.jpg",
      "LOGO": "http://app.homecaravan.net/uploads/logo_company/20170621205435.jpg",
      "FIRST_NAME": "Anthony",
      "LAST_NAME": "Hayes",
      "PHONE": "(314) 524-3495",
      "ACTION_REQUIRED": "yes",
      "ACTION_ACTIVE": "1",
      "INVITED_BY": "0",
      "USER_ID": "702",
      "ROLE_ID": "Buyer",
      "RECEPTIONIST": "no",
      "MESSAGE_COUNT": "0",
      "COMPANY": "First Team",
      "LISTING_ID": "175",
      "COMPANY_ADDRESS_1":"17737 Bushard St",
      "COMPANY_ADDRESS_2":"Fountain Valley, California"
    },
    {
      "ID": "703",
      "EMAIL": "james@yopmail.com",
      "STATUS": "active",
      "PHOTO": "http://app.homecaravan.net/uploads/account_avatar/20170717234259.jpg",
      "LOGO": "http://app.homecaravan.net/uploads/logo_company/20170620234730.jpg",
      "FIRST_NAME": "Alyssa",
      "LAST_NAME": "James",
      "PHONE": "(314) 524-3495",
      "ACTION_REQUIRED": "yes",
      "ACTION_ACTIVE": "1",
      "INVITED_BY": "0",
      "USER_ID": "703",
      "ROLE_ID": "Buyer",
      "RECEPTIONIST": "no",
      "MESSAGE_COUNT": "0",
      "COMPANY": "Realty ONE Group",
      "LISTING_ID": "175",
      "COMPANY_ADDRESS_1":"7631 Whitney Dr",
      "COMPANY_ADDRESS_2":"Huntington Beach, California"
    },
    {
      "ID": "704",
      "EMAIL": "robertagent@yopmail.com",
      "STATUS": "active",
      "LOGO": "http://app.homecaravan.net/uploads/logo_company/20170815233517.jpg",
      "PHOTO": "http://app.homecaravan.net/uploads/account_avatar/medium/20170711233237.jpg",
      "FIRST_NAME": "Robert",
      "LAST_NAME": "Miller",
      "PHONE": "(322) 422-6555",
      "ACTION_REQUIRED": "yes",
      "ACTION_ACTIVE": "1",
      "INVITED_BY": "0",
      "USER_ID": "704",
      "COMPANY": "Weichert",
      "LISTING_ID": "175",
      "ROLE_ID": "Agent",
      "RECEPTIONIST": "yes",
      "MESSAGE_COUNT": "28",
      "COMPANY_ADDRESS_1":"6448 Heil Ave",
      "COMPANY_ADDRESS_2":"Huntington Beach, California"
    },
    {
      "ID": "705",
      "EMAIL": "makayla@yopmail.com",
      "STATUS": "active",
      "LOGO": "http://app.homecaravan.net/uploads/logo_company/20170815233517.jpg",
      "PHOTO": "http://app.homecaravan.net/uploads/account_avatar/20170711233608.jpg",
      "FIRST_NAME": "Makayla",
      "LAST_NAME": "Moore",
      "PHONE": "(734) 914-9395",
      "ACTION_REQUIRED": "yes",
      "ACTION_ACTIVE": "1",
      "INVITED_BY": "0",
      "USER_ID": "705",
      "COMPANY": "Weichert",
      "LISTING_ID": "175",
      "ROLE_ID": "Agent",
      "RECEPTIONIST": "no",
      "MESSAGE_COUNT": "0",
      "COMPANY_ADDRESS_1":"5652 Littler Dr",
      "COMPANY_ADDRESS_2":"Huntington Beach, California"
    },
    {
      "ID": "706",
      "EMAIL": "davidtran@yopmail.com",
      "STATUS": "active",
      "LOGO": "http://app.homecaravan.net/uploads/logo_company/20170620234951.jpg",
      "PHOTO": "http://app.homecaravan.net/uploads/account_avatar/20170712010319.jpg",
      "FIRST_NAME": "David",
      "LAST_NAME": "Tran",
      "PHONE": "(632) 935-2236",
      "ACTION_REQUIRED": "yes",
      "ACTION_ACTIVE": "1",
      "INVITED_BY": "0",
      "USER_ID": "706",
      "COMPANY": "Remax",
      "LISTING_ID": "175",
      "ROLE_ID": "Agent",
      "RECEPTIONIST": "no",
      "MESSAGE_COUNT": "0",
      "COMPANY_ADDRESS_1":"15232 Tungwood St",
      "COMPANY_ADDRESS_2":"Westminster, California"
    },
    {
      "ID": "707",
      "EMAIL": "thomase@yopmail.com",
      "STATUS": "active",
      "LOGO": "http://app.homecaravan.net/uploads/logo_company/20170620234730.jpg",
      "PHOTO": "http://app.homecaravan.net/uploads/account_avatar/medium/20170721025400.jpg",
      "FIRST_NAME": "Thomas",
      "LAST_NAME": "Edison",
      "PHONE": "(853) 427-8143",
      "ACTION_REQUIRED": "yes",
      "ACTION_ACTIVE": "1",
      "INVITED_BY": "0",
      "USER_ID": "707",
      "COMPANY": "Realty ONE Group",
      "LISTING_ID": "175",
      "ROLE_ID": "Agent",
      "RECEPTIONIST": "no",
      "MESSAGE_COUNT": "0",
      "COMPANY_ADDRESS_1":"7631 Whitney Dr",
      "COMPANY_ADDRESS_2":"Huntington Beach, California"
    },
    {
      "ID": "708",
      "EMAIL": "WilsonMi@yopmail.com",
      "STATUS": "active",
      "PHOTO": "http://app.homecaravan.net/uploads/account_avatar/20170711232620.jpg",
      "LOGO": "http://app.homecaravan.net/uploads/logo_company/20170620234730.jpg",
      "FIRST_NAME": "Michael",
      "LAST_NAME": "Wilson",
      "PHONE": "(314) 524-3495",
      "ACTION_REQUIRED": "yes",
      "ACTION_ACTIVE": "1",
      "INVITED_BY": "0",
      "USER_ID": "708",
      "ROLE_ID": "Buyer",
      "RECEPTIONIST": "no",
      "MESSAGE_COUNT": "0",
      "COMPANY": "Realty ONE Group",
      "LISTING_ID": "175",
      "COMPANY_ADDRESS_1":"7631 Whitney Dr",
      "COMPANY_ADDRESS_2":"Huntington Beach, California"
    },
    {
      "ID": "709",
      "EMAIL": "samuel@yopmail.com",
      "STATUS": "active",
      "PHOTO": "http://app.homecaravan.net/uploads/account_avatar/medium/20170711233028.jpg",
      "LOGO": "http://app.homecaravan.net/uploads/logo_company/20170815233517.jpg",
      "FIRST_NAME": "Samuel",
      "LAST_NAME": "Anderson",
      "PHONE": "(314) 524-3495",
      "ACTION_REQUIRED": "yes",
      "ACTION_ACTIVE": "1",
      "INVITED_BY": "0",
      "USER_ID": "709",
      "ROLE_ID": "Buyer",
      "RECEPTIONIST": "no",
      "MESSAGE_COUNT": "0",
      "COMPANY": "Weichert",
      "LISTING_ID": "175",
      "COMPANY_ADDRESS_1":"5652 Littler Dr",
      "COMPANY_ADDRESS_2":"Huntington Beach, California"
    },
    {
      "ID": "710",
      "EMAIL": "owensm@yopmail.com",
      "STATUS": "active",
      "PHOTO": "http://app.homecaravan.net/uploads/account_avatar/20170717235958.jpg",
      "LOGO": "http://app.homecaravan.net/uploads/logo_company/20170815233517.jpg",
      "FIRST_NAME": "Owen",
      "LAST_NAME": "Smith",
      "PHONE": "(314) 524-3495",
      "ACTION_REQUIRED": "yes",
      "ACTION_ACTIVE": "1",
      "INVITED_BY": "0",
      "USER_ID": "710",
      "ROLE_ID": "Buyer",
      "RECEPTIONIST": "no",
      "MESSAGE_COUNT": "0",
      "COMPANY": "Weichert",
      "LISTING_ID": "175",
      "COMPANY_ADDRESS_1":"5652 Littler Dr",
      "COMPANY_ADDRESS_2":"Huntington Beach, California"
    },
    {
      "ID": "711",
      "EMAIL": "Howard@yopmail.com",
      "STATUS": "active",
      "PHOTO": "http://app.homecaravan.net/uploads/account_avatar/20170711233951.jpg",
      "LOGO": "http://app.homecaravan.net/uploads/logo_company/20170815233517.jpg",
      "FIRST_NAME": "Alan",
      "LAST_NAME": "Howard",
      "PHONE": "(314) 524-3495",
      "ACTION_REQUIRED": "yes",
      "ACTION_ACTIVE": "1",
      "INVITED_BY": "0",
      "USER_ID": "711",
      "ROLE_ID": "Buyer",
      "RECEPTIONIST": "no",
      "MESSAGE_COUNT": "0",
      "COMPANY": "Weichert",
      "LISTING_ID": "175",
      "COMPANY_ADDRESS_1":"5652 Littler Dr",
      "COMPANY_ADDRESS_2":"Huntington Beach, California"
    },
    {
      "ID": "712",
      "EMAIL": "Nicholas@yopmail.com",
      "STATUS": "active",
      "PHOTO": "http://app.homecaravan.net/uploads/account_avatar/20170711234244.jpg",
      "LOGO": "http://app.homecaravan.net/uploads/logo_company/20170815233517.jpg",
      "FIRST_NAME": "Nicholas",
      "LAST_NAME": "Gray",
      "PHONE": "(314) 524-3495",
      "ACTION_REQUIRED": "yes",
      "ACTION_ACTIVE": "1",
      "INVITED_BY": "0",
      "USER_ID": "712",
      "ROLE_ID": "Buyer",
      "RECEPTIONIST": "no",
      "MESSAGE_COUNT": "0",
      "COMPANY": "Weichert",
      "LISTING_ID": "175",
      "COMPANY_ADDRESS_1":"5652 Littler Dr",
      "COMPANY_ADDRESS_2":"Huntington Beach, California"
    },
    {
      "ID": "713",
      "EMAIL": "charles@yopmail.com",
      "STATUS": "active",
      "LOGO": "http://app.homecaravan.net/uploads/logo_company/20170815233517.jpg",
      "PHOTO": "http://app.homecaravan.net/uploads/account_avatar/medium/20170711232845.jpg",
      "FIRST_NAME": "Charles",
      "LAST_NAME": "Howard",
      "PHONE": "(224) 484-132",
      "ACTION_REQUIRED": "yes",
      "ACTION_ACTIVE": "1",
      "INVITED_BY": "0",
      "USER_ID": "713",
      "COMPANY": "Weichert",
      "LISTING_ID": "175",
      "ROLE_ID": "Agent",
      "RECEPTIONIST": "no",
      "MESSAGE_COUNT": "0",
      "COMPANY_ADDRESS_1":"8757 Slater Ave",
      "COMPANY_ADDRESS_2":"Fountain Valley, California"
    },
    {
      "ID": "714",
      "EMAIL": "Samantha@yopmail.com",
      "STATUS": "active",
      "PHOTO": "http://app.homecaravan.net/uploads/account_avatar/20170711234948.jpg",
      "LOGO": "http://app.homecaravan.net/uploads/logo_company/20170621205435.jpg",
      "FIRST_NAME": "Samantha",
      "LAST_NAME": "Powell",
      "PHONE": "(314) 524-3495",
      "ACTION_REQUIRED": "yes",
      "ACTION_ACTIVE": "1",
      "INVITED_BY": "0",
      "USER_ID": "714",
      "ROLE_ID": "Buyer",
      "RECEPTIONIST": "no",
      "MESSAGE_COUNT": "0",
      "COMPANY": "First Team",
      "LISTING_ID": "175",
      "COMPANY_ADDRESS_1":"17737 Bushard St",
      "COMPANY_ADDRESS_2":"Fountain Valley, California"
    },
    {
      "ID": "715",
      "EMAIL": "agent@gmail.com",
      "STATUS": "active",
      "LOGO": "http://app.homecaravan.net/uploads/logo_company/20170621205435.jpg",
      "PHOTO": "http://app.homecaravan.net/uploads/account_avatar/20170711205607.jpg",
      "FIRST_NAME": "Aadarsh",
      "LAST_NAME": "Thompson",
      "PHONE": "(314) 943-3351",
      "ACTION_REQUIRED": "yes",
      "ACTION_ACTIVE": "1",
      "INVITED_BY": "0",
      "USER_ID": "715",
      "COMPANY": "First Team",
      "LISTING_ID": "175",
      "ROLE_ID": "Agent",
      "RECEPTIONIST": "no",
      "MESSAGE_COUNT": "0",
      "COMPANY_ADDRESS_1":"17737 Bushard St",
      "COMPANY_ADDRESS_2":"Fountain Valley, California"
    },
    {
      "ID": "716",
      "EMAIL": "Sarah@yopmail.com",
      "STATUS": "active",
      "PHOTO": "http://app.homecaravan.net/uploads/account_avatar/20170711235629.jpg",
      "LOGO": "http://app.homecaravan.net/uploads/logo_company/20170621205435.jpg",
      "FIRST_NAME": "Sarah",
      "LAST_NAME": "Howard",
      "PHONE": "(314) 524-3495",
      "ACTION_REQUIRED": "yes",
      "ACTION_ACTIVE": "1",
      "INVITED_BY": "0",
      "USER_ID": "716",
      "ROLE_ID": "Buyer",
      "RECEPTIONIST": "no",
      "MESSAGE_COUNT": "0",
      "COMPANY": "First Team",
      "LISTING_ID": "175",
      "COMPANY_ADDRESS_1":"17737 Bushard St",
      "COMPANY_ADDRESS_2":"Fountain Valley, California"
    },
    {
      "ID": "717",
      "EMAIL": "breandan@yopmail.com",
      "STATUS": "active",
      "PHOTO": "http://app.homecaravan.net/uploads/account_avatar/20170711235754.jpg",
      "LOGO": "http://app.homecaravan.net/uploads/logo_company/20170620234730.jpg",
      "FIRST_NAME": "Breandan",
      "LAST_NAME": "Kelly",
      "PHONE": "(314) 524-3495",
      "ACTION_REQUIRED": "yes",
      "ACTION_ACTIVE": "1",
      "INVITED_BY": "0",
      "USER_ID": "717",
      "ROLE_ID": "Buyer",
      "RECEPTIONIST": "no",
      "MESSAGE_COUNT": "0",
      "COMPANY": "Realty ONE Group",
      "LISTING_ID": "175",
      "COMPANY_ADDRESS_1":"7631 Whitney Dr",
      "COMPANY_ADDRESS_2":"Huntington Beach, California"
    },
    {
      "ID": "718",
      "EMAIL": "Bryan@yopmail.com",
      "STATUS": "active",
      "PHOTO": "http://app.homecaravan.net/uploads/account_avatar/20170711201506.jpg",
      "LOGO": "http://app.homecaravan.net/uploads/logo_company/20170620234730.jpg",
      "FIRST_NAME": "Bryan",
      "LAST_NAME": "DiCarlo",
      "PHONE": "(314) 524-3495",
      "ACTION_REQUIRED": "yes",
      "ACTION_ACTIVE": "1",
      "INVITED_BY": "0",
      "USER_ID": "718",
      "ROLE_ID": "Agent",
      "RECEPTIONIST": "no",
      "MESSAGE_COUNT": "0",
      "COMPANY": "Realty ONE Group",
      "LISTING_ID": "175",
      "COMPANY_ADDRESS_1":"7631 Whitney Dr",
      "COMPANY_ADDRESS_2":"Huntington Beach, California"
    },
    {
      "ID": "719",
      "EMAIL": "Robert@yopmail.com",
      "STATUS": "active",
      "PHOTO": "http://app.homecaravan.net/uploads/account_avatar/20170711201733.jpg",
      "LOGO": "http://app.homecaravan.net/uploads/logo_company/20170807003935.jpg",
      "FIRST_NAME": "Robert",
      "LAST_NAME": "Thomas",
      "PHONE": "(314) 524-3495",
      "ACTION_REQUIRED": "yes",
      "ACTION_ACTIVE": "1",
      "INVITED_BY": "0",
      "USER_ID": "719",
      "ROLE_ID": "Inspector",
      "RECEPTIONIST": "no",
      "MESSAGE_COUNT": "0",
      "COMPANY": "Pelletiter",
      "LISTING_ID": "175",
      "COMPANY_ADDRESS_1":"17737 Bushard St",
      "COMPANY_ADDRESS_2":"Fountain Valley, California"
    },
    {
      "ID": "720",
      "EMAIL": "Robinson@yopmail.com",
      "STATUS": "active",
      "PHOTO": "http://app.homecaravan.net/uploads/account_avatar/20170711201917.jpg",
      "LOGO": "http://app.homecaravan.net/uploads/logo_company/20170813184320.jpg",
      "FIRST_NAME": "Mateo",
      "LAST_NAME": "Robinson",
      "PHONE": "(314) 524-3495",
      "ACTION_REQUIRED": "yes",
      "ACTION_ACTIVE": "1",
      "INVITED_BY": "0",
      "USER_ID": "720",
      "ROLE_ID": "Inspector",
      "RECEPTIONIST": "no",
      "MESSAGE_COUNT": "0",
      "COMPANY": "Haven",
      "LISTING_ID": "175",
      "COMPANY_ADDRESS_1":"5652 Littler Dr",
      "COMPANY_ADDRESS_2":"Huntington Beach, California"
    },
    {
      "ID": "721",
      "EMAIL": "Alyssa@yopmail.com",
      "STATUS": "active",
      "PHOTO": "http://app.homecaravan.net/uploads/account_avatar/20170711202624.jpg",
      "LOGO": "http://app.homecaravan.net/uploads/logo_company/20170807004419.jpg",
      "FIRST_NAME": "Alyssa",
      "LAST_NAME": "Harris",
      "PHONE": "(314) 524-3495",
      "ACTION_REQUIRED": "yes",
      "ACTION_ACTIVE": "1",
      "INVITED_BY": "0",
      "USER_ID": "721",
      "ROLE_ID": "Inspector",
      "RECEPTIONIST": "no",
      "MESSAGE_COUNT": "0",
      "COMPANY": "Hunter Home",
      "LISTING_ID": "175",
      "COMPANY_ADDRESS_1":"5652 Littler Dr",
      "COMPANY_ADDRESS_2":"Huntington Beach, California"
    },
    {
      "ID": "722",
      "EMAIL": "Audrey@yopmail.com",
      "STATUS": "active",
      "PHOTO": "http://app.homecaravan.net/uploads/account_avatar/20170711202814.jpg",
      "LOGO": "http://app.homecaravan.net/uploads/logo_company/20170807003714.jpg",
      "FIRST_NAME": "Audrey",
      "LAST_NAME": "Miller",
      "PHONE": "(314) 524-3495",
      "ACTION_REQUIRED": "yes",
      "ACTION_ACTIVE": "1",
      "INVITED_BY": "0",
      "USER_ID": "722",
      "ROLE_ID": "Inspector",
      "RECEPTIONIST": "no",
      "MESSAGE_COUNT": "0",
      "COMPANY": "Inspectro",
      "LISTING_ID": "175",
      "COMPANY_ADDRESS_1":"5652 Littler Dr",
      "COMPANY_ADDRESS_2":"Huntington Beach, California"
    },
    {
      "ID": "723",
      "EMAIL": "Edward@yopmail.com",
      "STATUS": "active",
      "PHOTO": "http://app.homecaravan.net/uploads/account_avatar/20170711203006.jpg",
      "LOGO": "http://app.homecaravan.net/uploads/logo_company/20170815233517.jpg",
      "FIRST_NAME": "Edward",
      "LAST_NAME": "Martinez",
      "PHONE": "(314) 524-3495",
      "ACTION_REQUIRED": "yes",
      "ACTION_ACTIVE": "1",
      "INVITED_BY": "0",
      "USER_ID": "723",
      "ROLE_ID": "Agent",
      "RECEPTIONIST": "no",
      "MESSAGE_COUNT": "0",
      "COMPANY": "Weichert",
      "LISTING_ID": "175",
      "COMPANY_ADDRESS_1":"5652 Littler Dr",
      "COMPANY_ADDRESS_2":"Huntington Beach, California"
    }

  ]
}
